LICENSE
pytest_spec2md/__init__.py
pytest_spec2md/plugin.py
pytest_spec2md/spec_creator.py
pytest_spec2md-0.5.0.dist-info/LICENSE
pytest_spec2md-0.5.0.dist-info/METADATA
pytest_spec2md-0.5.0.dist-info/WHEEL
pytest_spec2md-0.5.0.dist-info/entry_points.txt
pytest_spec2md-0.5.0.dist-info/RECORD
