Metadata-Version: 2.1
Name: pytest-spec2md
Version: 0.5.0
Summary: Library pytest-spec2md is a pytest plugin to create a markdown specification while running pytest.
Home-page: https://dev.azure.com/h7d/Quality/
License: GPL-2.0-or-later
Keywords: pytest,test,unittest,specification,markdown
Author: mh7d
Maintainer: mh7d
Requires-Python: >3.9,<4
Classifier: License :: OSI Approved :: GNU General Public License v2 or later (GPLv2+)
Classifier: Programming Language :: Python :: 3
Classifier: Programming Language :: Python :: 3.10
Classifier: Programming Language :: Python :: 3.11
Classifier: Programming Language :: Python :: 3.12
Classifier: Programming Language :: Python :: 3.9
Classifier: Topic :: Software Development :: Libraries
Classifier: Topic :: Software Development :: Testing
Classifier: Topic :: Utilities
Requires-Dist: backports_strenum (>1.2)
Requires-Dist: pytest (>7.0)
Project-URL: Repository, https://dev.azure.com/h7d/Quality/_git/pytest-spec2md
